README
ami_atlas
ami_atlas_post_install
setup.py
pyAMI_atlas/LICENSE.txt
pyAMI_atlas/__init__.py
pyAMI_atlas/api.py
pyAMI_atlas/config.py
pyAMI_atlas/license.txt
pyAMI_atlas/utils.py
pyAMI_atlas.egg-info/PKG-INFO
pyAMI_atlas.egg-info/SOURCES.txt
pyAMI_atlas.egg-info/dependency_links.txt
pyAMI_atlas.egg-info/not-zip-safe
pyAMI_atlas.egg-info/requires.txt
pyAMI_atlas.egg-info/top_level.txt